open_windsurf/__init__.py
open_windsurf/cli.py
open_windsurf/core.py
open_windsurf-0.1.2.dist-info/LICENSE
open_windsurf-0.1.2.dist-info/METADATA
open_windsurf-0.1.2.dist-info/WHEEL
open_windsurf-0.1.2.dist-info/entry_points.txt
open_windsurf-0.1.2.dist-info/RECORD
