Metadata-Version: 2.1
Name: open-windsurf
Version: 0.1.2
Summary: Open multiple Windsurf (VS Code-based) instances for different directories/paths
License: MIT
Author: Tom Dörr
Author-email: tomdoerr96@gmail.com
Requires-Python: >=3.8,<4.0
Classifier: License :: OSI Approved :: MIT License
Classifier: Programming Language :: Python :: 3
Classifier: Programming Language :: Python :: 3.8
Classifier: Programming Language :: Python :: 3.9
Classifier: Programming Language :: Python :: 3.10
Classifier: Programming Language :: Python :: 3.11
Classifier: Programming Language :: Python :: 3.12
Classifier: Programming Language :: Python :: 3.13
